pthost/__init__.py
pthost/_version.py
pthost/pthost.py
pthost/modules/__init__.py
pthost/modules/scanner.py
pthost-1.0.11.dist-info/licenses/LICENSE
pthost-1.0.11.dist-info/METADATA
pthost-1.0.11.dist-info/WHEEL
pthost-1.0.11.dist-info/entry_points.txt
pthost-1.0.11.dist-info/top_level.txt
pthost-1.0.11.dist-info/RECORD
