Metadata-Version: 2.4
Name: pthost
Version: 1.0.11
Summary: Default vhost tester
Home-page: https://www.penterep.com/
Author: Penterep
Author-email: info@penterep.com
License: GPLv3
Project-URL: homepage, https://www.penterep.com/
Project-URL: repository, https://github.com/penterep/pthost
Project-URL: tracker, https://github.com/penterep/pthost/issues
Classifier: Programming Language :: Python :: 3
Classifier: Programming Language :: Python :: Implementation :: CPython
Classifier: Environment :: Console
Classifier: Topic :: Security
Classifier: License :: OSI Approved :: GNU General Public License v3 (GPLv3)
Requires-Python: >=3.9
License-File: LICENSE
Requires-Dist: ptlibs<2,>=1.0.14
Requires-Dist: tldextract
Requires-Dist: validators
Requires-Dist: bs4
Dynamic: author
Dynamic: author-email
Dynamic: classifier
Dynamic: description
Dynamic: description-content-type
Dynamic: home-page
Dynamic: license
Dynamic: license-file
Dynamic: project-url
Dynamic: requires-dist
Dynamic: requires-python
Dynamic: summary
